models/__init__.py
models/post.py
showcase_ecommerce/START_HERE.py
showcase_ecommerce/__init__.py
showcase_ecommerce/advanced_benchmarks.py
showcase_ecommerce/advanced_features_demo.py
showcase_ecommerce/api.py
showcase_ecommerce/benchmarks.py
showcase_ecommerce/database.py
showcase_ecommerce/demo.py
showcase_ecommerce/docs.py
showcase_ecommerce/extensions_benchmarks.py
showcase_ecommerce/extensions_demo.py
showcase_ecommerce/models.py
showcase_ecommerce/orm_extensions.py
showcase_ecommerce/quickstart.py
showcase_ecommerce/services.py
turbo/__init__.py
turbo/__main__.py
turbo/advanced_features.py
turbo/anomaly.py
turbo/async_optimized.py
turbo/async_support.py
turbo/audit.py
turbo/audit_log.py
turbo/autoscale.py
turbo/blueprint.py
turbo/cache_redis.py
turbo/cdc.py
turbo/cdc_stream.py
turbo/circuit_breaker.py
turbo/cli.py
turbo/column_security.py
turbo/config.py
turbo/contracts.py
turbo/cursor_pagination.py
turbo/dashboard.py
turbo/data_masking.py
turbo/data_security.py
turbo/database.py
turbo/decorators.py
turbo/diff.py
turbo/events.py
turbo/exceptions.py
turbo/fields.py
turbo/graphql_gen.py
turbo/ha_manager.py
turbo/health.py
turbo/history.py
turbo/hotpath.py
turbo/json_query.py
turbo/lazy.py
turbo/migrations.py
turbo/model.py
turbo/multi_db.py
turbo/multitenancy.py
turbo/nlquery.py
turbo/online_ddl.py
turbo/optimized.py
turbo/optimizer.py
turbo/orm_extensions.py
turbo/pagination.py
turbo/performance.py
turbo/profiling.py
turbo/quality.py
turbo/quantum.py
turbo/query_builder.py
turbo/query_cache.py
turbo/query_optimizer.py
turbo/rate_limiting.py
turbo/rbac.py
turbo/recursive_query.py
turbo/replay.py
turbo/rest_gen.py
turbo/rules.py
turbo/search.py
turbo/seeder.py
turbo/soft_delete.py
turbo/sql_utils.py
turbo/subscriptions.py
turbo/temporal_query.py
turbo/tenant_router.py
turbo/testing_suites.py
turbo/threat_detection.py
turbo/tui.py
turbo/vector.py
turbo_orm-1.1.0.dist-info/licenses/LICENSE
turbo_orm-1.1.0.dist-info/METADATA
turbo_orm-1.1.0.dist-info/WHEEL
turbo_orm-1.1.0.dist-info/entry_points.txt
turbo_orm-1.1.0.dist-info/top_level.txt
turbo_orm-1.1.0.dist-info/RECORD
