Metadata-Version: 2.4
Name: turbo-orm
Version: 1.1.0
Summary: Ultra-fast Python ORM with enhanced error handling, monitoring, and type-safe configuration
Home-page: https://github.com/turbo-orm/turbo-orm
Author: Turbo ORM Team
Author-email: Turbo ORM Team <team@turbo-orm.dev>
Maintainer-email: Turbo ORM Team <team@turbo-orm.dev>
License: MIT License
Project-URL: Homepage, https://github.com/yourusername/turbo-orm
Project-URL: Documentation, https://turbo-orm.readthedocs.io
Project-URL: Repository, https://github.com/yourusername/turbo-orm
Project-URL: Bug Tracker, https://github.com/yourusername/turbo-orm/issues
Keywords: orm,database,sqlite,performance,async,turbo,fast,querybuilder,monitoring,health-check
Classifier: Development Status :: 5 - Production/Stable
Classifier: Intended Audience :: Developers
Classifier: Topic :: Database
Classifier: License :: OSI Approved :: MIT License
Classifier: Programming Language :: Python :: 3
Classifier: Programming Language :: Python :: 3.8
Classifier: Programming Language :: Python :: 3.9
Classifier: Programming Language :: Python :: 3.10
Classifier: Programming Language :: Python :: 3.11
Classifier: Programming Language :: Python :: 3.12
Classifier: Operating System :: OS Independent
Classifier: Environment :: Web Environment
Classifier: Framework :: AsyncIO
Classifier: Natural Language :: English
Classifier: Topic :: Software Development :: Libraries
Requires-Python: >=3.8
License-File: LICENSE
Provides-Extra: async
Requires-Dist: aiosqlite>=0.19.0; extra == "async"
Provides-Extra: redis
Requires-Dist: redis>=4.5.0; extra == "redis"
Provides-Extra: http
Requires-Dist: requests>=2.31.0; extra == "http"
Provides-Extra: dev
Requires-Dist: pytest>=7.4.0; extra == "dev"
Requires-Dist: pytest-asyncio>=0.21.0; extra == "dev"
Dynamic: author
Dynamic: home-page
Dynamic: license-file
Dynamic: requires-python
